contractme/__init__.py
contractme/annotations.py
contractme/contracting.py
contractme/py.typed
contractme/testing.py
contractme/typecheck.py
contractme-1.4.0.dist-info/METADATA
contractme-1.4.0.dist-info/WHEEL
contractme-1.4.0.dist-info/licenses/LICENSE
contractme-1.4.0.dist-info/RECORD
