Metadata-Version: 2.4
Name: contractme
Version: 1.4.0
Summary: A powerful, expressive and lightweight design-by-contract framework
Project-URL: Repository, https://gitlab.com/leogermond/contractme
Author-email: Leo Germond <leo.germond@gmail.com>
License-Expression: Apache-2.0
License-File: LICENSE
Requires-Python: >=3.13
Requires-Dist: annotated-types>=0.7.0
Requires-Dist: hypothesis>=6.131.9
